{"nodes": [{"id": "docs_codex_test_matrix", "label": "docs/codex/TEST_MATRIX.md", "file_type": "document", "source_file": "docs/codex/TEST_MATRIX.md", "source_location": null, "source_url": null, "captured_at": null, "author": null, "contributor": null}, {"id": "codex_test_matrix_test_matrix", "label": "Test Matrix (docs/codex/TEST_MATRIX.md)", "file_type": "document", "source_file": "docs/codex/TEST_MATRIX.md", "source_location": null, "source_url": null, "captured_at": null, "author": null, "contributor": null}, {"id": "codex_test_matrix", "label": "docs/codex/TEST_MATRIX.md", "file_type": "document", "source_file": "docs/codex/TEST_MATRIX.md", "source_location": null, "source_url": null, "captured_at": null, "author": null, "contributor": null}], "edges": [{"source": "codex_test_matrix_test_matrix", "target": "codex_commands_commands", "relation": "conceptually_related_to", "confidence": "INFERRED", "confidence_score": 0.85, "source_file": "docs/codex/TEST_MATRIX.md", "source_location": null, "weight": 1.0}, {"source": "codex_test_matrix_test_matrix", "target": "codex_env_index_env_index", "relation": "references", "confidence": "EXTRACTED", "confidence_score": 1.0, "source_file": "docs/codex/TEST_MATRIX.md", "source_location": null, "weight": 1.0}], "hyperedges": []}