{"nodes": [{"id": "c_users_fedet_documents_github_gymcontrol_codex_subagents_postgres_pro_md", "label": "postgres-pro.md", "file_type": "document", "source_file": ".codex/subagents/postgres-pro.md", "source_location": "L1"}, {"id": "subagents_postgres_pro_project_overlay", "label": "Project Overlay", "file_type": "document", "source_file": ".codex/subagents/postgres-pro.md", "source_location": "L8"}, {"id": "subagents_postgres_pro_communication_protocol", "label": "Communication Protocol", "file_type": "document", "source_file": ".codex/subagents/postgres-pro.md", "source_location": "L145"}, {"id": "subagents_postgres_pro_postgresql_context_assessment", "label": "PostgreSQL Context Assessment", "file_type": "document", "source_file": ".codex/subagents/postgres-pro.md", "source_location": "L147"}, {"id": "subagents_postgres_pro_development_workflow", "label": "Development Workflow", "file_type": "document", "source_file": ".codex/subagents/postgres-pro.md", "source_location": "L162"}, {"id": "subagents_postgres_pro_1_database_analysis", "label": "1. Database Analysis", "file_type": "document", "source_file": ".codex/subagents/postgres-pro.md", "source_location": "L166"}, {"id": "subagents_postgres_pro_2_implementation_phase", "label": "2. Implementation Phase", "file_type": "document", "source_file": ".codex/subagents/postgres-pro.md", "source_location": "L190"}, {"id": "subagents_postgres_pro_3_postgresql_excellence", "label": "3. PostgreSQL Excellence", "file_type": "document", "source_file": ".codex/subagents/postgres-pro.md", "source_location": "L228"}], "edges": [{"source": "c_users_fedet_documents_github_gymcontrol_codex_subagents_postgres_pro_md", "target": "subagents_postgres_pro_project_overlay", "relation": "contains", "confidence": "EXTRACTED", "source_file": ".codex/subagents/postgres-pro.md", "source_location": "L8", "weight": 1.0}, {"source": "subagents_postgres_pro_project_overlay", "target": "subagents_postgres_pro_communication_protocol", "relation": "contains", "confidence": "EXTRACTED", "source_file": ".codex/subagents/postgres-pro.md", "source_location": "L145", "weight": 1.0}, {"source": "subagents_postgres_pro_communication_protocol", "target": "subagents_postgres_pro_postgresql_context_assessment", "relation": "contains", "confidence": "EXTRACTED", "source_file": ".codex/subagents/postgres-pro.md", "source_location": "L147", "weight": 1.0}, {"source": "subagents_postgres_pro_project_overlay", "target": "subagents_postgres_pro_development_workflow", "relation": "contains", "confidence": "EXTRACTED", "source_file": ".codex/subagents/postgres-pro.md", "source_location": "L162", "weight": 1.0}, {"source": "subagents_postgres_pro_development_workflow", "target": "subagents_postgres_pro_1_database_analysis", "relation": "contains", "confidence": "EXTRACTED", "source_file": ".codex/subagents/postgres-pro.md", "source_location": "L166", "weight": 1.0}, {"source": "subagents_postgres_pro_development_workflow", "target": "subagents_postgres_pro_2_implementation_phase", "relation": "contains", "confidence": "EXTRACTED", "source_file": ".codex/subagents/postgres-pro.md", "source_location": "L190", "weight": 1.0}, {"source": "subagents_postgres_pro_development_workflow", "target": "subagents_postgres_pro_3_postgresql_excellence", "relation": "contains", "confidence": "EXTRACTED", "source_file": ".codex/subagents/postgres-pro.md", "source_location": "L228", "weight": 1.0}], "input_tokens": 0, "output_tokens": 0}